.coveragerc
.gitignore
.travis.yml
LICENSE.txt
README.md
setup.py
doc/COMPAT_SUMMARY.md
doc/PROPOSAL.md
examples/basic/alu.py
examples/basic/alu_hier.py
examples/basic/arst.py
examples/basic/cdc.py
examples/basic/ctr.py
examples/basic/ctr_en.py
examples/basic/fsm.py
examples/basic/gpio.py
examples/basic/inst.py
examples/basic/mem.py
examples/basic/pmux.py
examples/basic/por.py
examples/basic/sel.py
examples/basic/uart.py
examples/board/01_blinky.py
examples/board/02_domain.py
nmigen/__init__.py
nmigen/_toolchain.py
nmigen/_unused.py
nmigen/_utils.py
nmigen/asserts.py
nmigen/cli.py
nmigen/rpc.py
nmigen/tracer.py
nmigen/utils.py
nmigen.egg-info/PKG-INFO
nmigen.egg-info/SOURCES.txt
nmigen.egg-info/dependency_links.txt
nmigen.egg-info/entry_points.txt
nmigen.egg-info/requires.txt
nmigen.egg-info/top_level.txt
nmigen/back/__init__.py
nmigen/back/pysim.py
nmigen/back/rtlil.py
nmigen/back/verilog.py
nmigen/build/__init__.py
nmigen/build/dsl.py
nmigen/build/plat.py
nmigen/build/res.py
nmigen/build/run.py
nmigen/compat/__init__.py
nmigen/compat/fhdl/__init__.py
nmigen/compat/fhdl/bitcontainer.py
nmigen/compat/fhdl/conv_output.py
nmigen/compat/fhdl/decorators.py
nmigen/compat/fhdl/module.py
nmigen/compat/fhdl/specials.py
nmigen/compat/fhdl/structure.py
nmigen/compat/fhdl/verilog.py
nmigen/compat/genlib/__init__.py
nmigen/compat/genlib/cdc.py
nmigen/compat/genlib/coding.py
nmigen/compat/genlib/fifo.py
nmigen/compat/genlib/fsm.py
nmigen/compat/genlib/record.py
nmigen/compat/genlib/resetsync.py
nmigen/compat/sim/__init__.py
nmigen/hdl/__init__.py
nmigen/hdl/ast.py
nmigen/hdl/cd.py
nmigen/hdl/dsl.py
nmigen/hdl/ir.py
nmigen/hdl/mem.py
nmigen/hdl/rec.py
nmigen/hdl/xfrm.py
nmigen/lib/__init__.py
nmigen/lib/cdc.py
nmigen/lib/coding.py
nmigen/lib/fifo.py
nmigen/lib/io.py
nmigen/test/__init__.py
nmigen/test/test_build_dsl.py
nmigen/test/test_build_plat.py
nmigen/test/test_build_res.py
nmigen/test/test_compat.py
nmigen/test/test_examples.py
nmigen/test/test_hdl_ast.py
nmigen/test/test_hdl_cd.py
nmigen/test/test_hdl_dsl.py
nmigen/test/test_hdl_ir.py
nmigen/test/test_hdl_mem.py
nmigen/test/test_hdl_rec.py
nmigen/test/test_hdl_xfrm.py
nmigen/test/test_lib_cdc.py
