Metadata-Version: 1.2
Name: nmigen
Version: 0.2
Summary: Python toolbox for building complex digital hardware
Home-page: UNKNOWN
Author: whitequark
Author-email: whitequark@whitequark.org
License: BSD
Project-URL: Source Code, https://github.com/nmigen/nmigen
Project-URL: Bug Tracker, https://github.com/nmigen/nmigen/issues
Platform: UNKNOWN
Requires-Python: ~=3.6
